etlstat/__init__.py
etlstat/database/__init__.py
etlstat/database/mysql.py
etlstat/database/oracle.py
etlstat/database/postgresql.py
etlstat/database/test/__init__.py
etlstat/database/test/test_mysql.py
etlstat/database/test/test_oracle.py
etlstat/database/test/test_postgresql.py
etlstat/database/test/test_sqlloader.py
etlstat/extractor/__init__.py
etlstat/extractor/extractor.py
etlstat/extractor/test/__init__.py
etlstat/extractor/test/test_extractor.py
etlstat/log/__init__.py
etlstat/log/logging.py
etlstat/log/timing.py
etlstat/text/__init__.py
etlstat/text/utils.py
etlstat/text/test/__init__.py
etlstat/text/test/test_utils.py
etlstat-0.6.1.dist-info/LICENSE.txt
etlstat-0.6.1.dist-info/METADATA
etlstat-0.6.1.dist-info/WHEEL
etlstat-0.6.1.dist-info/top_level.txt
etlstat-0.6.1.dist-info/RECORD
